statman/__init__.py
statman/calculation.py
statman/gauge.py
statman/history.py
statman/metric.py
statman/rate.py
statman/statman.py
statman/stopwatch.py
statman-1.4.6.dist-info/LICENSE
statman-1.4.6.dist-info/METADATA
statman-1.4.6.dist-info/WHEEL
statman-1.4.6.dist-info/top_level.txt
statman-1.4.6.dist-info/RECORD
