Metadata-Version: 2.1
Name: statman
Version: 1.4.6
Summary: Collection of metrics collection tools, including a simple stopwatch
Author: Mighty Pulpo
Author-email: jayray.net@gmail.com
Keywords: stats,metrics,stopwatch,timing,performance,monitoring
Classifier: Programming Language :: Python :: 3
Classifier: License :: OSI Approved :: MIT License
Classifier: Operating System :: OS Independent
Requires-Python: >=3.6
License-File: LICENSE
Requires-Dist: is-numeric ==1.0.1
